coroICA-0.1.25.dist-info/DESCRIPTION.rst
coroICA-0.1.25.dist-info/METADATA
coroICA-0.1.25.dist-info/RECORD
coroICA-0.1.25.dist-info/WHEEL
coroICA-0.1.25.dist-info/metadata.json
coroICA-0.1.25.dist-info/pbr.json
coroICA-0.1.25.dist-info/top_level.txt
coroica/__init__.py
coroica/coroica.py
coroica/utils.py
coroica/uwedge.py
coroica/uwedgeica.py
coroica/tests/__init__.py
coroica/tests/test_common.py
coroica/tests/test_uwedge.py
