Metadata-Version: 2.0
Name: coroICA
Version: 0.1.25
Summary: coroICA (scikit-learn compatible)
Home-page: http://github.com/sweichwald/coroICA-python
Author: Niklas Pfister and Sebastian Weichwald
Author-email: UNKNOWN
License: AGPL-3.0
Platform: UNKNOWN
Classifier: Intended Audience :: Developers
Classifier: Intended Audience :: Science/Research
Classifier: License :: OSI Approved :: GNU Affero General Public License v3
Classifier: Programming Language :: Python
Classifier: Topic :: Scientific/Engineering
Classifier: Topic :: Software Development
Requires-Dist: numpy (>=1.8.2)
Requires-Dist: scikit-learn (>=0.17)
Requires-Dist: scipy (>=0.13.3)
